README.md
pyproject.toml
setup.cfg
setup.py
runloop/__init__.py
runloop.egg-info/PKG-INFO
runloop.egg-info/SOURCES.txt
runloop.egg-info/dependency_links.txt
runloop.egg-info/top_level.txt
runloop/loops/__init__.py
runloop/loops/loop.py
tests/__init__.py
tests/test_packaging.py
tests/lambdas/__init__.py
tests/lambdas/test_lambdas.py