Metadata-Version: 2.1
Name: runloop
Version: 0.1
Summary: hey there
